falcon/__init__.py
falcon/config.py
falcon/constants.py
falcon/datasets.py
falcon/main.py
falcon/runtime.py
falcon/serialization.py
falcon/sklapi.py
falcon/task_configurations.py
falcon/type_guessing.py
falcon/types.py
falcon/utils.py
falcon/abstract/__init__.py
falcon/abstract/learner.py
falcon/abstract/model.py
falcon/abstract/onnx_convertible.py
falcon/abstract/optuna.py
falcon/abstract/processor.py
falcon/abstract/task_manager.py
falcon/abstract/task_pipeline.py
falcon/addons/sklearn/__init__.py
falcon/addons/sklearn/decomposition/svd.py
falcon/addons/sklearn/ensemble/balanced_stacking.py
falcon/addons/sklearn/model_selection/balanced_strat_kfold.py
falcon/addons/sklearn/preprocessing/date_tokenizer.py
falcon/tabular/__init__.py
falcon/tabular/configurations.py
falcon/tabular/reporting.py
falcon/tabular/tabular_manager.py
falcon/tabular/utils.py
falcon/tabular/wrappers.py
falcon/tabular/adapters/ts/adapter.py
falcon/tabular/adapters/ts/auxiliary.py
falcon/tabular/adapters/ts/learner.py
falcon/tabular/adapters/ts/pipeline.py
falcon/tabular/adapters/ts/plot_errors.py
falcon/tabular/learners/__init__.py
falcon/tabular/learners/optuna_learner.py
falcon/tabular/learners/plain_learner.py
falcon/tabular/learners/super_learner.py
falcon/tabular/models/__init__.py
falcon/tabular/models/hist_gbt.py
falcon/tabular/models/stacking.py
falcon/tabular/pipelines/__init__.py
falcon/tabular/pipelines/simple_tabular_pipeline.py
falcon/tabular/processors/__init__.py
falcon/tabular/processors/label_decoder.py
falcon/tabular/processors/multi_modal_encoder.py
falcon/tabular/processors/scaler_and_encoder.py
falcon_ml-0.7.0.dist-info/LICENSE
falcon_ml-0.7.0.dist-info/METADATA
falcon_ml-0.7.0.dist-info/WHEEL
falcon_ml-0.7.0.dist-info/top_level.txt
falcon_ml-0.7.0.dist-info/RECORD
