Metadata-Version: 2.1
Name: falcon-ml
Version: 0.7.0
Summary: AutoML library for fast experementations.
Author-email: Oleg Kostromin <kostromin97@gmail.com>, Iryna Kondrashchenko <iryna230520@gmail.com>, Marco Pasini <marco.pasini.98@gmail.com>
License: MIT
Classifier: Programming Language :: Python :: 3
Classifier: License :: OSI Approved :: MIT License
Classifier: Operating System :: OS Independent
Requires-Python: >=3.9
License-File: LICENSE
Requires-Dist: skl2onnx >=1.12.0
Requires-Dist: scikit-learn >=1.1.0
Requires-Dist: numpy >=1.18.0
Requires-Dist: onnx >=1.12.0
Requires-Dist: onnxruntime >=1.12.1
Requires-Dist: pandas >=1.0.0
Requires-Dist: imbalanced-learn >=0.8.1
Requires-Dist: pyarrow >=8.0.0
Requires-Dist: optuna >=3.0.0
Requires-Dist: packaging >=20.0.0
Requires-Dist: phonnx >=0.0.1
